{
  "^bedrock-proxypass-json$": {
    "hiddenPackets": {
      "serverbound": ["move_player", "player_action", "level_sound_event"],
      "clientbound": ["level_chunk", "update_block", "network_chunk_publisher_update", "set_entity_motion", "move_entity_absolute", "set_entity_data", "level_sound_event"]
    }
  },
  "^java-node-minecraft-protocol-.*$": {
    "hiddenPackets": {
      "serverbound": ["position", "position_look", "look", "keep_alive", "entity_action"],
      "clientbound": ["keep_alive", "update_time", "rel_entity_move", "entity_teleport", "map_chunk", "update_light", "update_view_position", "entity_metadata", "entity_update_attributes", "unload_chunk", "entity_velocity", "entity_move_look", "entity_head_rotation"]
    }
  }
}